s3_storage_stats/__init__.py
s3_storage_stats/args.py
s3_storage_stats/base.py
s3_storage_stats/logger.py
s3_storage_stats-1.0.9.data/scripts/s3-storage-stats
storage_stats/__init__.py
storage_stats/args.py
storage_stats/base.py
storage_stats/logger.py
s3_storage_stats-1.0.9.dist-info/METADATA
s3_storage_stats-1.0.9.dist-info/WHEEL
s3_storage_stats-1.0.9.dist-info/top_level.txt
s3_storage_stats-1.0.9.dist-info/RECORD
